sc_scraper/__init__.py
sc_scraper/main.py
sc_scraper-0.1.0.dist-info/METADATA
sc_scraper-0.1.0.dist-info/WHEEL
sc_scraper-0.1.0.dist-info/top_level.txt
sc_scraper-0.1.0.dist-info/RECORD
