Metadata-Version: 2.1
Name: sc-scraper
Version: 0.1.0
Summary: Scraper for Soundcloud
Home-page: https://github.com/maximizzar/sc_scraper
Author: maximizzar
Author-email: mail@maximizzar.de
Classifier: Programming Language :: Python :: 3
Classifier: License :: OSI Approved :: GNU Affero General Public License v3
Classifier: Operating System :: OS Independent
Requires-Python: >=3.6
